dox/commands.py
dox/runner.py
dox/__init__.py
dox/cmd.py
dox/images.py
dox/tests/base.py
dox/tests/test_cmd.py
dox/tests/test_dox.py
dox/tests/__init__.py
dox/tests/test_runner.py
dox/tests/test_images.py
dox/tests/samples/dox.yaml
dox/tests/samples/dox-old.yaml
dox/tests/samples/tox.ini
dox/tests/config/test_travis_yaml.py
dox/tests/config/__init__.py
dox/tests/config/test_dox_yaml.py
dox/tests/config/test_commands.py
dox/tests/config/test_tox_ini.py
dox/config/travis_yaml.py
dox/config/base.py
dox/config/tox_ini.py
dox/config/dockerfile.py
dox/config/__init__.py
dox/config/cmdline.py
dox/config/dox_yaml.py
dox-0.2.0.dist-info/METADATA
dox-0.2.0.dist-info/WHEEL
dox-0.2.0.dist-info/entry_points.txt
dox-0.2.0.dist-info/metadata.json
dox-0.2.0.dist-info/RECORD
dox-0.2.0.dist-info/top_level.txt
dox-0.2.0.dist-info/DESCRIPTION.rst
dox-0.2.0.dist-info/pbr.json
